<?xml version="1.0" encoding="UTF-8"?>
<tasks><task><id>2</id><task>Mow the lawn</task><priority>2</priority><size>3</size><group>2</group><deadline/><status>1</status><flag/></task><task><id>3</id><task>Wash the car</task><priority>3</priority><size>2</size><group>1</group><deadline/><status/><flag> </flag></task><task><id>4</id><task>Paint the fence</task><priority>1</priority><size>2</size><group>1</group><deadline/><status/><flag/></task><task><id>6</id><task>Intramural hockey game</task><priority>1</priority><size>2</size><group>4</group><deadline/><status>2</status><flag/></task><task><id>7</id><task>Canucks hockey game</task><priority>3</priority><size>3</size><group>4</group><deadline>20170305</deadline><status/><flag/></task></tasks>
